evoflow/VERSION
evoflow/__info__.py
evoflow/__init__.py
evoflow/__main__.py
evoflow/base.py
evoflow/cli.py
evoflow/params.py
evoflow/version.py
evoflow/controller/__init__.py
evoflow/controller/common_step_controller.py
evoflow/controller/log_controller.py
evoflow/controller/visualize_controller.py
evoflow/controller/data_manipulate/__init__.py
evoflow/controller/data_manipulate/data_manipulate.py
evoflow/controller/data_manipulate/excel_file_operator.py
evoflow/controller/data_manipulate/file_operator.py
evoflow/controller/data_manipulate/image_file_operator.py
evoflow/controller/data_manipulate/pdf_file_operator.py
evoflow/controller/data_manipulate/pptx_file_operator.py
evoflow/entities/__init__.py
evoflow/entities/global_vars.py
evoflow/entities/common/__init__.py
evoflow/entities/common/step/__init__.py
evoflow/entities/common/step/downloader.py
evoflow/entities/common/step/open_excel_file.py
evoflow/entities/common/step/browser/__init__.py
evoflow/entities/common/step/file_operator/__init__.py
evoflow/entities/core/__init__.py
evoflow/entities/core/base_object.py
evoflow/entities/core/condition.py
evoflow/entities/core/job.py
evoflow/entities/core/session.py
evoflow/entities/core/step.py
evoflow/entities/core/step_list.py
evoflow/entities/core/transaction.py
evoflow/entities/core/workflow.py
evoflow/entities/data_manipulate/__init__.py
evoflow/entities/data_manipulate/abstract_data.py
evoflow/entities/data_manipulate/file_operator/__init__.py
evoflow/entities/data_manipulate/file_operator/dataframe_file.py
evoflow/entities/data_manipulate/file_operator/file.py
evoflow/entities/data_manipulate/file_operator/image_file.py
evoflow/entities/data_manipulate/file_operator/pdf_file.py
evoflow/entities/data_manipulate/file_operator/pptx_file.py
evoflow/entities/exceptions/__init__.py
evoflow/entities/exceptions/base_exception.py
evoflow/entities/exceptions/evo_exception.py
evoflow/operators/__init__.py
evoflow/operators/base_operator.py
evodflow-0.1.9.5.dist-info/LICENSE
evodflow-0.1.9.5.dist-info/METADATA
evodflow-0.1.9.5.dist-info/WHEEL
evodflow-0.1.9.5.dist-info/entry_points.txt
evodflow-0.1.9.5.dist-info/top_level.txt
evodflow-0.1.9.5.dist-info/RECORD
