Metadata-Version: 2.1
Name: evodflow
Version: 0.1.9.5
Summary: Awesome evoflow created by maycuatroi
Home-page: https://github.com/maycuatroi/evo-flow/
Author: maycuatroi
License-File: LICENSE
Requires-Dist: tqdm
Requires-Dist: rich
Requires-Dist: python-pptx
Requires-Dist: json-tricks
Requires-Dist: xlrd
Requires-Dist: openpyxl
Requires-Dist: coloredlogs
Requires-Dist: pyunpack
Requires-Dist: patool
Provides-Extra: test
Requires-Dist: pytest ; extra == 'test'
Requires-Dist: coverage ; extra == 'test'
Requires-Dist: flake8 ; extra == 'test'
Requires-Dist: black ; extra == 'test'
Requires-Dist: isort ; extra == 'test'
Requires-Dist: pytest-cov ; extra == 'test'
Requires-Dist: codecov ; extra == 'test'
Requires-Dist: mypy ; extra == 'test'
Requires-Dist: gitchangelog ; extra == 'test'
Requires-Dist: mkdocs ; extra == 'test'
